{"pagelen": 50, "values": [{"update": {"description": "As a future work, the code that infers the ubuntu distro could be shared with ignition.dsl file.\r\n\r\n[Tested with the gz11 branch](https://build.osrfoundation.org/view/All/job/sdformat-ci-pr_any-ubuntu_auto-amd64/1/console).", "title": "Implement the ubuntu_auto testing job for sdformat. Support for g++8", "destination": {"commit": {"hash": "16df3cc2a70c", "type": "commit", "links": {"self": {"href": "data/repositories/osrf/release-tools/commit/16df3cc2a70c.json"}, "html": {"href": "#!/osrf/release-tools/commits/16df3cc2a70c"}}}, "repository": {"links": {"self": {"href": "data/repositories/osrf/release-tools.json"}, "html": {"href": "#!/osrf/release-tools"}, "avatar": {"href": "data/bytebucket.org/ravatar/{41811d3d-19d0-428e-a134-976595e72508}ts=python"}}, "type": "repository", "name": "release-tools", "full_name": "osrf/release-tools", "uuid": "{41811d3d-19d0-428e-a134-976595e72508}"}, "branch": {"name": "default"}}, "reason": "", "source": {"commit": {"hash": "878362577264", "type": "commit", "links": {"self": {"href": "data/repositories/osrf/release-tools/commit/878362577264.json"}, "html": {"href": "#!/osrf/release-tools/commits/878362577264"}}}, "repository": {"links": {"self": {"href": "data/repositories/osrf/release-tools.json"}, "html": {"href": "#!/osrf/release-tools"}, "avatar": {"href": "data/bytebucket.org/ravatar/{41811d3d-19d0-428e-a134-976595e72508}ts=python"}}, "type": "repository", "name": "release-tools", "full_name": "osrf/release-tools", "uuid": "{41811d3d-19d0-428e-a134-976595e72508}"}, "branch": {"name": "sdformat_auto_ci"}}, "state": "MERGED", "author": {"display_name": "Jose Luis Rivero", "uuid": "{d12309b2-f745-42ee-b119-aec4fcdf81fe}", "links": {"self": {"href": "https://api.bitbucket.org/2.0/users/%7Bd12309b2-f745-42ee-b119-aec4fcdf81fe%7D"}, "html": {"href": "https://bitbucket.org/%7Bd12309b2-f745-42ee-b119-aec4fcdf81fe%7D/"}, "avatar": {"href": "data/secure.gravatar.com/avatar/109284c8b83411dbc7492138f6167e9ed=httpsavatar-management--avatars.us-west-2.prod.public.atl-paas.netinitialsJR-5.png"}}, "nickname": "Jose Luis Rivero", "type": "user", "account_id": "557058:155a32e2-420c-4d50-98e0-0e722f63f906"}, "date": "2018-07-24T10:34:10.847462+00:00"}, "pull_request": {"type": "pullrequest", "id": 607, "links": {"self": {"href": "data/repositories/osrf/release-tools/pullrequests/607.json"}, "html": {"href": "#!/osrf/release-tools/pull-requests/607"}}, "title": "Implement the ubuntu_auto testing job for sdformat. Support for g++8"}}, {"approval": {"date": "2018-07-20T15:40:46.047255+00:00", "pullrequest": {"type": "pullrequest", "id": 607, "links": {"self": {"href": "data/repositories/osrf/release-tools/pullrequests/607.json"}, "html": {"href": "#!/osrf/release-tools/pull-requests/607"}}, "title": "Implement the ubuntu_auto testing job for sdformat. Support for g++8"}, "user": {"display_name": "Nate Koenig", "uuid": "{c862cdd9-fcc8-4419-9fc7-e20db14b8fcb}", "links": {"self": {"href": "https://api.bitbucket.org/2.0/users/%7Bc862cdd9-fcc8-4419-9fc7-e20db14b8fcb%7D"}, "html": {"href": "https://bitbucket.org/%7Bc862cdd9-fcc8-4419-9fc7-e20db14b8fcb%7D/"}, "avatar": {"href": "https://avatar-management--avatars.us-west-2.prod.public.atl-paas.net/557058:095b1e12-74ed-4e20-b44f-2f0745b616e0/ca24bb11-4787-4b14-a20d-d91835e9bde2/128"}}, "nickname": "Nathan Koenig", "type": "user", "account_id": "557058:095b1e12-74ed-4e20-b44f-2f0745b616e0"}}, "pull_request": {"type": "pullrequest", "id": 607, "links": {"self": {"href": "data/repositories/osrf/release-tools/pullrequests/607.json"}, "html": {"href": "#!/osrf/release-tools/pull-requests/607"}}, "title": "Implement the ubuntu_auto testing job for sdformat. Support for g++8"}}, {"comment": {"links": {"self": {"href": "data/repositories/osrf/release-tools/pullrequests/607/comments/69955318.json"}, "html": {"href": "#!/osrf/release-tools/pull-requests/607/_/diff#comment-69955318"}}, "deleted": false, "pullrequest": {"type": "pullrequest", "id": 607, "links": {"self": {"href": "data/repositories/osrf/release-tools/pullrequests/607.json"}, "html": {"href": "#!/osrf/release-tools/pull-requests/607"}}, "title": "Implement the ubuntu_auto testing job for sdformat. Support for g++8"}, "content": {"raw": "The build is still failing due to the lack of ignition-math6 in the build. I'll fix that in a new PR \\(`sdformat_auto_ci_deps`  branch\\)", "markup": "markdown", "html": "<p>The build is still failing due to the lack of ignition-math6 in the build. I'll fix that in a new PR (<code>sdformat_auto_ci_deps</code>  branch)</p>", "type": "rendered"}, "created_on": "2018-07-13T22:52:15.378111+00:00", "user": {"display_name": "Jose Luis Rivero", "uuid": "{d12309b2-f745-42ee-b119-aec4fcdf81fe}", "links": {"self": {"href": "https://api.bitbucket.org/2.0/users/%7Bd12309b2-f745-42ee-b119-aec4fcdf81fe%7D"}, "html": {"href": "https://bitbucket.org/%7Bd12309b2-f745-42ee-b119-aec4fcdf81fe%7D/"}, "avatar": {"href": "data/secure.gravatar.com/avatar/109284c8b83411dbc7492138f6167e9ed=httpsavatar-management--avatars.us-west-2.prod.public.atl-paas.netinitialsJR-5.png"}}, "nickname": "Jose Luis Rivero", "type": "user", "account_id": "557058:155a32e2-420c-4d50-98e0-0e722f63f906"}, "updated_on": "2018-07-16T09:57:33.890074+00:00", "type": "pullrequest_comment", "id": 69955318}, "pull_request": {"type": "pullrequest", "id": 607, "links": {"self": {"href": "data/repositories/osrf/release-tools/pullrequests/607.json"}, "html": {"href": "#!/osrf/release-tools/pull-requests/607"}}, "title": "Implement the ubuntu_auto testing job for sdformat. Support for g++8"}}, {"update": {"description": "As a future work, the code that infers the ubuntu distro could be shared with ignition.dsl file.\r\n\r\n[Tested with the gz11 branch](https://build.osrfoundation.org/view/All/job/sdformat-ci-pr_any-ubuntu_auto-amd64/1/console).", "title": "Implement the ubuntu_auto testing job for sdformat. Support for g++8", "destination": {"commit": {"hash": "7a8c12b0980f", "type": "commit", "links": {"self": {"href": "data/repositories/osrf/release-tools/commit/7a8c12b0980f.json"}, "html": {"href": "#!/osrf/release-tools/commits/7a8c12b0980f"}}}, "repository": {"links": {"self": {"href": "data/repositories/osrf/release-tools.json"}, "html": {"href": "#!/osrf/release-tools"}, "avatar": {"href": "data/bytebucket.org/ravatar/{41811d3d-19d0-428e-a134-976595e72508}ts=python"}}, "type": "repository", "name": "release-tools", "full_name": "osrf/release-tools", "uuid": "{41811d3d-19d0-428e-a134-976595e72508}"}, "branch": {"name": "default"}}, "reason": "", "source": {"commit": {"hash": "878362577264", "type": "commit", "links": {"self": {"href": "data/repositories/osrf/release-tools/commit/878362577264.json"}, "html": {"href": "#!/osrf/release-tools/commits/878362577264"}}}, "repository": {"links": {"self": {"href": "data/repositories/osrf/release-tools.json"}, "html": {"href": "#!/osrf/release-tools"}, "avatar": {"href": "data/bytebucket.org/ravatar/{41811d3d-19d0-428e-a134-976595e72508}ts=python"}}, "type": "repository", "name": "release-tools", "full_name": "osrf/release-tools", "uuid": "{41811d3d-19d0-428e-a134-976595e72508}"}, "branch": {"name": "sdformat_auto_ci"}}, "state": "OPEN", "author": {"display_name": "Jose Luis Rivero", "uuid": "{d12309b2-f745-42ee-b119-aec4fcdf81fe}", "links": {"self": {"href": "https://api.bitbucket.org/2.0/users/%7Bd12309b2-f745-42ee-b119-aec4fcdf81fe%7D"}, "html": {"href": "https://bitbucket.org/%7Bd12309b2-f745-42ee-b119-aec4fcdf81fe%7D/"}, "avatar": {"href": "data/secure.gravatar.com/avatar/109284c8b83411dbc7492138f6167e9ed=httpsavatar-management--avatars.us-west-2.prod.public.atl-paas.netinitialsJR-5.png"}}, "nickname": "Jose Luis Rivero", "type": "user", "account_id": "557058:155a32e2-420c-4d50-98e0-0e722f63f906"}, "date": "2018-07-13T22:49:41.764780+00:00"}, "pull_request": {"type": "pullrequest", "id": 607, "links": {"self": {"href": "data/repositories/osrf/release-tools/pullrequests/607.json"}, "html": {"href": "#!/osrf/release-tools/pull-requests/607"}}, "title": "Implement the ubuntu_auto testing job for sdformat. Support for g++8"}}, {"update": {"description": "As a future work, the code that infers the ubuntu distro could be shared with ignition.dsl file. \r\n\r\n[Tested with the gz11 branch](https://build.osrfoundation.org/view/All/job/sdformat-ci-pr_any-ubuntu_auto-amd64/1/console).", "title": "Implement the ubuntu_auto testing job for sdformat", "destination": {"commit": {"hash": "7a8c12b0980f", "type": "commit", "links": {"self": {"href": "data/repositories/osrf/release-tools/commit/7a8c12b0980f.json"}, "html": {"href": "#!/osrf/release-tools/commits/7a8c12b0980f"}}}, "repository": {"links": {"self": {"href": "data/repositories/osrf/release-tools.json"}, "html": {"href": "#!/osrf/release-tools"}, "avatar": {"href": "data/bytebucket.org/ravatar/{41811d3d-19d0-428e-a134-976595e72508}ts=python"}}, "type": "repository", "name": "release-tools", "full_name": "osrf/release-tools", "uuid": "{41811d3d-19d0-428e-a134-976595e72508}"}, "branch": {"name": "default"}}, "reason": "", "source": {"commit": {"hash": "878362577264", "type": "commit", "links": {"self": {"href": "data/repositories/osrf/release-tools/commit/878362577264.json"}, "html": {"href": "#!/osrf/release-tools/commits/878362577264"}}}, "repository": {"links": {"self": {"href": "data/repositories/osrf/release-tools.json"}, "html": {"href": "#!/osrf/release-tools"}, "avatar": {"href": "data/bytebucket.org/ravatar/{41811d3d-19d0-428e-a134-976595e72508}ts=python"}}, "type": "repository", "name": "release-tools", "full_name": "osrf/release-tools", "uuid": "{41811d3d-19d0-428e-a134-976595e72508}"}, "branch": {"name": "sdformat_auto_ci"}}, "state": "OPEN", "author": {"display_name": "Jose Luis Rivero", "uuid": "{d12309b2-f745-42ee-b119-aec4fcdf81fe}", "links": {"self": {"href": "https://api.bitbucket.org/2.0/users/%7Bd12309b2-f745-42ee-b119-aec4fcdf81fe%7D"}, "html": {"href": "https://bitbucket.org/%7Bd12309b2-f745-42ee-b119-aec4fcdf81fe%7D/"}, "avatar": {"href": "data/secure.gravatar.com/avatar/109284c8b83411dbc7492138f6167e9ed=httpsavatar-management--avatars.us-west-2.prod.public.atl-paas.netinitialsJR-5.png"}}, "nickname": "Jose Luis Rivero", "type": "user", "account_id": "557058:155a32e2-420c-4d50-98e0-0e722f63f906"}, "date": "2018-07-13T22:37:19.224022+00:00"}, "pull_request": {"type": "pullrequest", "id": 607, "links": {"self": {"href": "data/repositories/osrf/release-tools/pullrequests/607.json"}, "html": {"href": "#!/osrf/release-tools/pull-requests/607"}}, "title": "Implement the ubuntu_auto testing job for sdformat. Support for g++8"}}, {"update": {"description": "As a future work, the code that infers the ubuntu distro could be shared with ignition.dsl file. \r\n\r\n[Tested with the gz11 branch](https://build.osrfoundation.org/view/All/job/sdformat-ci-pr_any-ubuntu_auto-amd64/1/console).", "title": "Implement the ubuntu_auto testing job for sdformat", "destination": {"commit": {"hash": "7a8c12b0980f", "type": "commit", "links": {"self": {"href": "data/repositories/osrf/release-tools/commit/7a8c12b0980f.json"}, "html": {"href": "#!/osrf/release-tools/commits/7a8c12b0980f"}}}, "repository": {"links": {"self": {"href": "data/repositories/osrf/release-tools.json"}, "html": {"href": "#!/osrf/release-tools"}, "avatar": {"href": "data/bytebucket.org/ravatar/{41811d3d-19d0-428e-a134-976595e72508}ts=python"}}, "type": "repository", "name": "release-tools", "full_name": "osrf/release-tools", "uuid": "{41811d3d-19d0-428e-a134-976595e72508}"}, "branch": {"name": "default"}}, "reason": "", "source": {"commit": {"hash": "a069db998b06", "type": "commit", "links": {"self": {"href": "data/repositories/osrf/release-tools/commit/a069db998b06.json"}, "html": {"href": "#!/osrf/release-tools/commits/a069db998b06"}}}, "repository": {"links": {"self": {"href": "data/repositories/osrf/release-tools.json"}, "html": {"href": "#!/osrf/release-tools"}, "avatar": {"href": "data/bytebucket.org/ravatar/{41811d3d-19d0-428e-a134-976595e72508}ts=python"}}, "type": "repository", "name": "release-tools", "full_name": "osrf/release-tools", "uuid": "{41811d3d-19d0-428e-a134-976595e72508}"}, "branch": {"name": "sdformat_auto_ci"}}, "state": "OPEN", "author": {"display_name": "Jose Luis Rivero", "uuid": "{d12309b2-f745-42ee-b119-aec4fcdf81fe}", "links": {"self": {"href": "https://api.bitbucket.org/2.0/users/%7Bd12309b2-f745-42ee-b119-aec4fcdf81fe%7D"}, "html": {"href": "https://bitbucket.org/%7Bd12309b2-f745-42ee-b119-aec4fcdf81fe%7D/"}, "avatar": {"href": "data/secure.gravatar.com/avatar/109284c8b83411dbc7492138f6167e9ed=httpsavatar-management--avatars.us-west-2.prod.public.atl-paas.netinitialsJR-5.png"}}, "nickname": "Jose Luis Rivero", "type": "user", "account_id": "557058:155a32e2-420c-4d50-98e0-0e722f63f906"}, "date": "2018-07-13T20:16:10.961938+00:00"}, "pull_request": {"type": "pullrequest", "id": 607, "links": {"self": {"href": "data/repositories/osrf/release-tools/pullrequests/607.json"}, "html": {"href": "#!/osrf/release-tools/pull-requests/607"}}, "title": "Implement the ubuntu_auto testing job for sdformat. Support for g++8"}}, {"update": {"description": "As a future work, the code that infers the ubuntu distro could be shared with ignition.dsl file. \r\n\r\n[Tested with the gz11 branch](https://build.osrfoundation.org/view/All/job/sdformat-ci-pr_any-ubuntu_auto-amd64/1/console).", "title": "Implement the ubuntu_auto testing job for sdformat", "destination": {"commit": {"hash": "7a8c12b0980f", "type": "commit", "links": {"self": {"href": "data/repositories/osrf/release-tools/commit/7a8c12b0980f.json"}, "html": {"href": "#!/osrf/release-tools/commits/7a8c12b0980f"}}}, "repository": {"links": {"self": {"href": "data/repositories/osrf/release-tools.json"}, "html": {"href": "#!/osrf/release-tools"}, "avatar": {"href": "data/bytebucket.org/ravatar/{41811d3d-19d0-428e-a134-976595e72508}ts=python"}}, "type": "repository", "name": "release-tools", "full_name": "osrf/release-tools", "uuid": "{41811d3d-19d0-428e-a134-976595e72508}"}, "branch": {"name": "default"}}, "reason": "", "source": {"commit": {"hash": "2555d2d0c297", "type": "commit", "links": {"self": {"href": "data/repositories/osrf/release-tools/commit/2555d2d0c297.json"}, "html": {"href": "#!/osrf/release-tools/commits/2555d2d0c297"}}}, "repository": {"links": {"self": {"href": "data/repositories/osrf/release-tools.json"}, "html": {"href": "#!/osrf/release-tools"}, "avatar": {"href": "data/bytebucket.org/ravatar/{41811d3d-19d0-428e-a134-976595e72508}ts=python"}}, "type": "repository", "name": "release-tools", "full_name": "osrf/release-tools", "uuid": "{41811d3d-19d0-428e-a134-976595e72508}"}, "branch": {"name": "sdformat_auto_ci"}}, "state": "OPEN", "author": {"display_name": "Jose Luis Rivero", "uuid": "{d12309b2-f745-42ee-b119-aec4fcdf81fe}", "links": {"self": {"href": "https://api.bitbucket.org/2.0/users/%7Bd12309b2-f745-42ee-b119-aec4fcdf81fe%7D"}, "html": {"href": "https://bitbucket.org/%7Bd12309b2-f745-42ee-b119-aec4fcdf81fe%7D/"}, "avatar": {"href": "data/secure.gravatar.com/avatar/109284c8b83411dbc7492138f6167e9ed=httpsavatar-management--avatars.us-west-2.prod.public.atl-paas.netinitialsJR-5.png"}}, "nickname": "Jose Luis Rivero", "type": "user", "account_id": "557058:155a32e2-420c-4d50-98e0-0e722f63f906"}, "date": "2018-07-13T20:09:46.332075+00:00"}, "pull_request": {"type": "pullrequest", "id": 607, "links": {"self": {"href": "data/repositories/osrf/release-tools/pullrequests/607.json"}, "html": {"href": "#!/osrf/release-tools/pull-requests/607"}}, "title": "Implement the ubuntu_auto testing job for sdformat. Support for g++8"}}, {"update": {"description": "As a future work, the code that infers the ubuntu distro could be shared with ignition.dsl file. \r\n\r\n[Tested with the gz11 branch](https://build.osrfoundation.org/view/All/job/sdformat-ci-pr_any-ubuntu_auto-amd64/1/console).", "title": "Implement the ubuntu_auto testing job for sdformat", "destination": {"commit": {"hash": "7a8c12b0980f", "type": "commit", "links": {"self": {"href": "data/repositories/osrf/release-tools/commit/7a8c12b0980f.json"}, "html": {"href": "#!/osrf/release-tools/commits/7a8c12b0980f"}}}, "repository": {"links": {"self": {"href": "data/repositories/osrf/release-tools.json"}, "html": {"href": "#!/osrf/release-tools"}, "avatar": {"href": "data/bytebucket.org/ravatar/{41811d3d-19d0-428e-a134-976595e72508}ts=python"}}, "type": "repository", "name": "release-tools", "full_name": "osrf/release-tools", "uuid": "{41811d3d-19d0-428e-a134-976595e72508}"}, "branch": {"name": "default"}}, "reason": "", "source": {"commit": {"hash": "981083ffe361", "type": "commit", "links": {"self": {"href": "data/repositories/osrf/release-tools/commit/981083ffe361.json"}, "html": {"href": "#!/osrf/release-tools/commits/981083ffe361"}}}, "repository": {"links": {"self": {"href": "data/repositories/osrf/release-tools.json"}, "html": {"href": "#!/osrf/release-tools"}, "avatar": {"href": "data/bytebucket.org/ravatar/{41811d3d-19d0-428e-a134-976595e72508}ts=python"}}, "type": "repository", "name": "release-tools", "full_name": "osrf/release-tools", "uuid": "{41811d3d-19d0-428e-a134-976595e72508}"}, "branch": {"name": "sdformat_auto_ci"}}, "state": "OPEN", "author": {"display_name": "Jose Luis Rivero", "uuid": "{d12309b2-f745-42ee-b119-aec4fcdf81fe}", "links": {"self": {"href": "https://api.bitbucket.org/2.0/users/%7Bd12309b2-f745-42ee-b119-aec4fcdf81fe%7D"}, "html": {"href": "https://bitbucket.org/%7Bd12309b2-f745-42ee-b119-aec4fcdf81fe%7D/"}, "avatar": {"href": "data/secure.gravatar.com/avatar/109284c8b83411dbc7492138f6167e9ed=httpsavatar-management--avatars.us-west-2.prod.public.atl-paas.netinitialsJR-5.png"}}, "nickname": "Jose Luis Rivero", "type": "user", "account_id": "557058:155a32e2-420c-4d50-98e0-0e722f63f906"}, "date": "2018-07-13T19:46:09.941291+00:00"}, "pull_request": {"type": "pullrequest", "id": 607, "links": {"self": {"href": "data/repositories/osrf/release-tools/pullrequests/607.json"}, "html": {"href": "#!/osrf/release-tools/pull-requests/607"}}, "title": "Implement the ubuntu_auto testing job for sdformat. Support for g++8"}}, {"update": {"description": "As a future work, the code that infers the ubuntu distro could be shared with ignition.dsl file. \r\n\r\n[Tested with the gz11 branch](https://build.osrfoundation.org/view/All/job/sdformat-ci-pr_any-ubuntu_auto-amd64/1/console).", "title": "Implement the ubuntu_auto testing job for sdformat", "destination": {"commit": {"hash": "7a8c12b0980f", "type": "commit", "links": {"self": {"href": "data/repositories/osrf/release-tools/commit/7a8c12b0980f.json"}, "html": {"href": "#!/osrf/release-tools/commits/7a8c12b0980f"}}}, "repository": {"links": {"self": {"href": "data/repositories/osrf/release-tools.json"}, "html": {"href": "#!/osrf/release-tools"}, "avatar": {"href": "data/bytebucket.org/ravatar/{41811d3d-19d0-428e-a134-976595e72508}ts=python"}}, "type": "repository", "name": "release-tools", "full_name": "osrf/release-tools", "uuid": "{41811d3d-19d0-428e-a134-976595e72508}"}, "branch": {"name": "default"}}, "reason": "", "source": {"commit": {"hash": "981083ffe361", "type": "commit", "links": {"self": {"href": "data/repositories/osrf/release-tools/commit/981083ffe361.json"}, "html": {"href": "#!/osrf/release-tools/commits/981083ffe361"}}}, "repository": {"links": {"self": {"href": "data/repositories/osrf/release-tools.json"}, "html": {"href": "#!/osrf/release-tools"}, "avatar": {"href": "data/bytebucket.org/ravatar/{41811d3d-19d0-428e-a134-976595e72508}ts=python"}}, "type": "repository", "name": "release-tools", "full_name": "osrf/release-tools", "uuid": "{41811d3d-19d0-428e-a134-976595e72508}"}, "branch": {"name": "sdformat_auto_ci"}}, "state": "OPEN", "author": {"display_name": "Jose Luis Rivero", "uuid": "{d12309b2-f745-42ee-b119-aec4fcdf81fe}", "links": {"self": {"href": "https://api.bitbucket.org/2.0/users/%7Bd12309b2-f745-42ee-b119-aec4fcdf81fe%7D"}, "html": {"href": "https://bitbucket.org/%7Bd12309b2-f745-42ee-b119-aec4fcdf81fe%7D/"}, "avatar": {"href": "data/secure.gravatar.com/avatar/109284c8b83411dbc7492138f6167e9ed=httpsavatar-management--avatars.us-west-2.prod.public.atl-paas.netinitialsJR-5.png"}}, "nickname": "Jose Luis Rivero", "type": "user", "account_id": "557058:155a32e2-420c-4d50-98e0-0e722f63f906"}, "date": "2018-07-13T19:46:09.900118+00:00"}, "pull_request": {"type": "pullrequest", "id": 607, "links": {"self": {"href": "data/repositories/osrf/release-tools/pullrequests/607.json"}, "html": {"href": "#!/osrf/release-tools/pull-requests/607"}}, "title": "Implement the ubuntu_auto testing job for sdformat. Support for g++8"}}]}