{"pagelen": 50, "values": [{"update": {"description": "After merging [#!/osrf/release-tools/pull-requests/661/support-for-node-selection-in-debbuild/diff](#!/osrf/release-tools/pull-requests/661/support-for-node-selection-in-debbuild/diff) a side effect is that the node selection mechanism is being propagated to th `repository_uploader` job \\(which should only run in master\\). This seems to me like  a bug already reported.\r\n\r\nTo avoid it, we can hardcode the `JENKINS_NODE_TAG`parameter to `master`when we call the repository\\_uploader script.", "title": "Workaround to repository_uploader to avoid propagation of machine selection", "destination": {"commit": {"hash": "38d9e44c5e0e", "type": "commit", "links": {"self": {"href": "data/repositories/osrf/release-tools/commit/38d9e44c5e0e.json"}, "html": {"href": "#!/osrf/release-tools/commits/38d9e44c5e0e"}}}, "repository": {"links": {"self": {"href": "data/repositories/osrf/release-tools.json"}, "html": {"href": "#!/osrf/release-tools"}, "avatar": {"href": "data/bytebucket.org/ravatar/{41811d3d-19d0-428e-a134-976595e72508}ts=python"}}, "type": "repository", "name": "release-tools", "full_name": "osrf/release-tools", "uuid": "{41811d3d-19d0-428e-a134-976595e72508}"}, "branch": {"name": "default"}}, "reason": "", "source": {"commit": {"hash": "f942f0e0a88b", "type": "commit", "links": {"self": {"href": "data/repositories/osrf/release-tools/commit/f942f0e0a88b.json"}, "html": {"href": "#!/osrf/release-tools/commits/f942f0e0a88b"}}}, "repository": {"links": {"self": {"href": "data/repositories/osrf/release-tools.json"}, "html": {"href": "#!/osrf/release-tools"}, "avatar": {"href": "data/bytebucket.org/ravatar/{41811d3d-19d0-428e-a134-976595e72508}ts=python"}}, "type": "repository", "name": "release-tools", "full_name": "osrf/release-tools", "uuid": "{41811d3d-19d0-428e-a134-976595e72508}"}, "branch": {"name": "fix_uploader"}}, "state": "MERGED", "author": {"display_name": "Steve Peters", "uuid": "{2ccfed09-18b8-4921-8d58-15ef01092802}", "links": {"self": {"href": "https://api.bitbucket.org/2.0/users/%7B2ccfed09-18b8-4921-8d58-15ef01092802%7D"}, "html": {"href": "https://bitbucket.org/%7B2ccfed09-18b8-4921-8d58-15ef01092802%7D/"}, "avatar": {"href": "data/secure.gravatar.com/avatar/1fb4816dad9e68337d3096f750951f6cd=httpsavatar-management--avatars.us-west-2.prod.public.atl-paas.netinitialsSP-1.png"}}, "nickname": "Steven Peters", "type": "user", "account_id": "557058:5de38267-b118-494c-aa76-4fab35448816"}, "date": "2018-11-09T08:50:21.262289+00:00"}, "pull_request": {"type": "pullrequest", "id": 691, "links": {"self": {"href": "data/repositories/osrf/release-tools/pullrequests/691.json"}, "html": {"href": "#!/osrf/release-tools/pull-requests/691"}}, "title": "Workaround to repository_uploader to avoid propagation of machine selection"}}, {"approval": {"date": "2018-11-06T23:46:23.445934+00:00", "pullrequest": {"type": "pullrequest", "id": 691, "links": {"self": {"href": "data/repositories/osrf/release-tools/pullrequests/691.json"}, "html": {"href": "#!/osrf/release-tools/pull-requests/691"}}, "title": "Workaround to repository_uploader to avoid propagation of machine selection"}, "user": {"display_name": "Steve Peters", "uuid": "{2ccfed09-18b8-4921-8d58-15ef01092802}", "links": {"self": {"href": "https://api.bitbucket.org/2.0/users/%7B2ccfed09-18b8-4921-8d58-15ef01092802%7D"}, "html": {"href": "https://bitbucket.org/%7B2ccfed09-18b8-4921-8d58-15ef01092802%7D/"}, "avatar": {"href": "data/secure.gravatar.com/avatar/1fb4816dad9e68337d3096f750951f6cd=httpsavatar-management--avatars.us-west-2.prod.public.atl-paas.netinitialsSP-1.png"}}, "nickname": "Steven Peters", "type": "user", "account_id": "557058:5de38267-b118-494c-aa76-4fab35448816"}}, "pull_request": {"type": "pullrequest", "id": 691, "links": {"self": {"href": "data/repositories/osrf/release-tools/pullrequests/691.json"}, "html": {"href": "#!/osrf/release-tools/pull-requests/691"}}, "title": "Workaround to repository_uploader to avoid propagation of machine selection"}}, {"update": {"description": "After merging [#!/osrf/release-tools/pull-requests/661/support-for-node-selection-in-debbuild/diff](#!/osrf/release-tools/pull-requests/661/support-for-node-selection-in-debbuild/diff) a side effect is that the node selection mechanism is being propagated to th `repository_uploader` job \\(which should only run in master\\). This seems to me like  a bug already reported.\r\n\r\nTo avoid it, we can hardcode the `JENKINS_NODE_TAG`parameter to `master`when we call the repository\\_uploader script.", "title": "Workaround to repository_uploader to avoid propagation of machine selection", "destination": {"commit": {"hash": "cc88d1dbd560", "type": "commit", "links": {"self": {"href": "data/repositories/osrf/release-tools/commit/cc88d1dbd560.json"}, "html": {"href": "#!/osrf/release-tools/commits/cc88d1dbd560"}}}, "repository": {"links": {"self": {"href": "data/repositories/osrf/release-tools.json"}, "html": {"href": "#!/osrf/release-tools"}, "avatar": {"href": "data/bytebucket.org/ravatar/{41811d3d-19d0-428e-a134-976595e72508}ts=python"}}, "type": "repository", "name": "release-tools", "full_name": "osrf/release-tools", "uuid": "{41811d3d-19d0-428e-a134-976595e72508}"}, "branch": {"name": "default"}}, "reason": "", "source": {"commit": {"hash": "f942f0e0a88b", "type": "commit", "links": {"self": {"href": "data/repositories/osrf/release-tools/commit/f942f0e0a88b.json"}, "html": {"href": "#!/osrf/release-tools/commits/f942f0e0a88b"}}}, "repository": {"links": {"self": {"href": "data/repositories/osrf/release-tools.json"}, "html": {"href": "#!/osrf/release-tools"}, "avatar": {"href": "data/bytebucket.org/ravatar/{41811d3d-19d0-428e-a134-976595e72508}ts=python"}}, "type": "repository", "name": "release-tools", "full_name": "osrf/release-tools", "uuid": "{41811d3d-19d0-428e-a134-976595e72508}"}, "branch": {"name": "fix_uploader"}}, "state": "OPEN", "author": {"display_name": "Jose Luis Rivero", "uuid": "{d12309b2-f745-42ee-b119-aec4fcdf81fe}", "links": {"self": {"href": "https://api.bitbucket.org/2.0/users/%7Bd12309b2-f745-42ee-b119-aec4fcdf81fe%7D"}, "html": {"href": "https://bitbucket.org/%7Bd12309b2-f745-42ee-b119-aec4fcdf81fe%7D/"}, "avatar": {"href": "data/secure.gravatar.com/avatar/109284c8b83411dbc7492138f6167e9ed=httpsavatar-management--avatars.us-west-2.prod.public.atl-paas.netinitialsJR-5.png"}}, "nickname": "Jose Luis Rivero", "type": "user", "account_id": "557058:155a32e2-420c-4d50-98e0-0e722f63f906"}, "date": "2018-11-06T23:43:58.931284+00:00"}, "pull_request": {"type": "pullrequest", "id": 691, "links": {"self": {"href": "data/repositories/osrf/release-tools/pullrequests/691.json"}, "html": {"href": "#!/osrf/release-tools/pull-requests/691"}}, "title": "Workaround to repository_uploader to avoid propagation of machine selection"}}, {"update": {"description": "After merging [#!/osrf/release-tools/pull-requests/661/support-for-node-selection-in-debbuild/diff](#!/osrf/release-tools/pull-requests/661/support-for-node-selection-in-debbuild/diff) a side effect is that the node selection mechanism is being propagated to th `repository_uploader` job \\(which should only run in master\\). This seems to me like  a bug already reported.\r\n\r\nTo avoid it, we can hardcode the `JENKINS_NODE_TAG`parameter to `master`when we call the repository\\_uploader script.", "title": "Workaround to repository_uploader to avoid propagation of machine selection", "destination": {"commit": {"hash": "cc88d1dbd560", "type": "commit", "links": {"self": {"href": "data/repositories/osrf/release-tools/commit/cc88d1dbd560.json"}, "html": {"href": "#!/osrf/release-tools/commits/cc88d1dbd560"}}}, "repository": {"links": {"self": {"href": "data/repositories/osrf/release-tools.json"}, "html": {"href": "#!/osrf/release-tools"}, "avatar": {"href": "data/bytebucket.org/ravatar/{41811d3d-19d0-428e-a134-976595e72508}ts=python"}}, "type": "repository", "name": "release-tools", "full_name": "osrf/release-tools", "uuid": "{41811d3d-19d0-428e-a134-976595e72508}"}, "branch": {"name": "default"}}, "reason": "", "source": {"commit": {"hash": "f942f0e0a88b", "type": "commit", "links": {"self": {"href": "data/repositories/osrf/release-tools/commit/f942f0e0a88b.json"}, "html": {"href": "#!/osrf/release-tools/commits/f942f0e0a88b"}}}, "repository": {"links": {"self": {"href": "data/repositories/osrf/release-tools.json"}, "html": {"href": "#!/osrf/release-tools"}, "avatar": {"href": "data/bytebucket.org/ravatar/{41811d3d-19d0-428e-a134-976595e72508}ts=python"}}, "type": "repository", "name": "release-tools", "full_name": "osrf/release-tools", "uuid": "{41811d3d-19d0-428e-a134-976595e72508}"}, "branch": {"name": "fix_uploader"}}, "state": "OPEN", "author": {"display_name": "Jose Luis Rivero", "uuid": "{d12309b2-f745-42ee-b119-aec4fcdf81fe}", "links": {"self": {"href": "https://api.bitbucket.org/2.0/users/%7Bd12309b2-f745-42ee-b119-aec4fcdf81fe%7D"}, "html": {"href": "https://bitbucket.org/%7Bd12309b2-f745-42ee-b119-aec4fcdf81fe%7D/"}, "avatar": {"href": "data/secure.gravatar.com/avatar/109284c8b83411dbc7492138f6167e9ed=httpsavatar-management--avatars.us-west-2.prod.public.atl-paas.netinitialsJR-5.png"}}, "nickname": "Jose Luis Rivero", "type": "user", "account_id": "557058:155a32e2-420c-4d50-98e0-0e722f63f906"}, "date": "2018-11-06T23:43:58.895545+00:00"}, "pull_request": {"type": "pullrequest", "id": 691, "links": {"self": {"href": "data/repositories/osrf/release-tools/pullrequests/691.json"}, "html": {"href": "#!/osrf/release-tools/pull-requests/691"}}, "title": "Workaround to repository_uploader to avoid propagation of machine selection"}}]}